hhframe/__init__.py
hhframe/hhConfig.py
hhframe/hhCrypto.py
hhframe/hhDecorator.py
hhframe/hhDouban.py
hhframe/hhExcel.py
hhframe/hhJson.py
hhframe/hhKuaiProxy.py
hhframe/hhMock.py
hhframe/hhMysql.py
hhframe/hhOs.py
hhframe/hhQiniu.py
hhframe/hhRequest.py
hhframe/hhResult.py
hhframe/hhUrl.py
hhframe/hhUtils.py
hhframe-0.6.0.dist-info/METADATA
hhframe-0.6.0.dist-info/WHEEL
hhframe-0.6.0.dist-info/top_level.txt
hhframe-0.6.0.dist-info/RECORD
