Metadata-Version: 2.4
Name: hhframe
Version: 0.6.0
Summary: houheaven frame for python
Author-email: 立树 <970012685@qq.com>
License: MIT
Project-URL: Homepage, http://plugin.houheaven.com/hhframe
Project-URL: Documentation, http://plugin.houheaven.com/hhframe
Project-URL: Repository, http://plugin.houheaven.com/hhframe
Project-URL: Issues, http://plugin.houheaven.com/hhframe
Keywords: hhframe,houheaven,后天堂
Classifier: Programming Language :: Python :: 3
Classifier: License :: OSI Approved :: MIT License
Classifier: Operating System :: OS Independent
Requires-Python: >=3.6
Requires-Dist: requests>=2.32.3
Requires-Dist: pymysql>=1.1.1
Requires-Dist: pycryptodome>=3.22.0
Requires-Dist: faker>=37.1.0
Requires-Dist: urllib3>=2.3.0
Requires-Dist: xlwt>=1.3.0
Requires-Dist: PyExecJs>=1.5.1
Requires-Dist: bs4>=0.0.1
